LICENSE
MANIFEST.in
README.md
setup.cfg
setup.py
herald/__init__.py
herald/admin.py
herald/apps.py
herald/base.py
herald/models.py
herald/text_notification.py
herald/urls.py
herald/views.py
herald/clients/__init__.py
herald/clients/msg91.py
herald/contrib/__init__.py
herald/contrib/auth/__init__.py
herald/contrib/auth/apps.py
herald/contrib/auth/forms.py
herald/contrib/auth/notifications.py
herald/contrib/auth/templates/herald/html/password_reset.html
herald/contrib/auth/templates/herald/text/password_reset.txt
herald/management/__init__.py
herald/management/commands/__init__.py
herald/management/commands/delnotifs.py
herald/migrations/0001_initial.py
herald/migrations/0002_sentnotification_attachments.py
herald/migrations/0003_auto_20170830_1617.py
herald/migrations/0004_auto_20171009_0906.py
herald/migrations/0005_auto_20180516_1755.py
herald/migrations/0006_auto_20190503_0625.py
herald/migrations/0007_auto_20190503_0832.py
herald/migrations/0008_auto_20190503_1320.py
herald/migrations/0009_sentnotification_receiver_doctor_profile_id.py
herald/migrations/0010_auto_20190904_0315.py
herald/migrations/__init__.py
herald/templates/herald/test/notification_list.html
mindbogglr_django_herald.egg-info/PKG-INFO
mindbogglr_django_herald.egg-info/SOURCES.txt
mindbogglr_django_herald.egg-info/dependency_links.txt
mindbogglr_django_herald.egg-info/requires.txt
mindbogglr_django_herald.egg-info/top_level.txt