Metadata-Version: 2.1
Name: mindbogglr-django-herald
Version: 0.2.19
Summary: Django library for separating the message content from transmission method
Home-page: https://github.com/pranay16/mindbogglr-django-herald/
Author: Pranay Majmundar
Author-email: pranay@mindbogglr.com
License: MIT
Download-URL: https://github.com/pranay16/mindbogglr-django-herald/tarball/0.2.19
Keywords: django,notifications,messaging
Platform: UNKNOWN
Classifier: Framework :: Django
Classifier: Intended Audience :: Developers
Classifier: Programming Language :: Python
Classifier: Programming Language :: Python :: 2
Classifier: Programming Language :: Python :: 2.7
Classifier: Programming Language :: Python :: 3
Classifier: Programming Language :: Python :: 3.3
Classifier: Programming Language :: Python :: 3.4
Classifier: Programming Language :: Python :: 3.5
Classifier: License :: OSI Approved :: MIT License
